medtools/__init__.py
medtools/types.py
medtools/tools/__init__.py
medtools/tools/ascvd.py
medtools-0.0.5.dist-info/LICENSE
medtools-0.0.5.dist-info/METADATA
medtools-0.0.5.dist-info/WHEEL
medtools-0.0.5.dist-info/top_level.txt
medtools-0.0.5.dist-info/RECORD
