Metadata-Version: 2.1
Name: medtools
Version: 0.0.5
Summary: MedTools by MedinfoX Group
Home-page: https://github.com/medinfox/medtools/
Author: medinfox
License-File: LICENSE
Requires-Dist: beautifulsoup4
Requires-Dist: langchain-core
Requires-Dist: pydantic
Requires-Dist: types-requests
Provides-Extra: test
Requires-Dist: pytest; extra == "test"
Requires-Dist: coverage; extra == "test"
Requires-Dist: flake8; extra == "test"
Requires-Dist: black; extra == "test"
Requires-Dist: isort; extra == "test"
Requires-Dist: pytest-cov; extra == "test"
Requires-Dist: mypy; extra == "test"
Requires-Dist: gitchangelog; extra == "test"
Requires-Dist: mkdocs; extra == "test"
